coworks-0.9.4.dist-info/METADATA
coworks-0.9.4.dist-info/WHEEL
coworks-0.9.4.dist-info/entry_points.txt
coworks-0.9.4.dist-info/licenses/LICENSE.txt
coworks-0.9.4.dist-info/licenses/NOTICE
coworks/__init__.py
coworks/aws.py
coworks/biz/__init__.py
coworks/biz/group.py
coworks/biz/operators.py
coworks/biz/sensors.py
coworks/blueprint/admin_blueprint.py
coworks/blueprint/mail_blueprint.py
coworks/blueprint/okta_blueprint.py
coworks/blueprint/profiler_blueprint.py
coworks/blueprint/test_blueprint.py
coworks/coworks.py
coworks/cws/__init__.py
coworks/cws/client.py
coworks/cws/command.py
coworks/cws/deploy.py
coworks/cws/exception.py
coworks/cws/new.py
coworks/cws/project_templates/README.md
coworks/cws/project_templates/tech/app.py
coworks/cws/project_templates/template.env
coworks/cws/templates/deploy.j2
coworks/cws/templates/project.cws.yml
coworks/cws/templates/terraform.j2
coworks/cws/templates/terraform/lambda.j2
coworks/cws/templates/terraform/local.j2
coworks/cws/templates/terraform/output.j2
coworks/cws/templates/terraform/provider.j2
coworks/cws/templates/terraform/request_templates.j2
coworks/cws/templates/terraform/response_templates.j2
coworks/cws/templates/terraform/rest_api.j2
coworks/cws/templates/terraform/role.j2
coworks/cws/utils.py
coworks/extension/jsonapi/__init__.py
coworks/extension/jsonapi/data.py
coworks/extension/jsonapi/fetching.py
coworks/extension/jsonapi/jsonapi.py
coworks/extension/jsonapi/query.py
coworks/extension/odoo.py
coworks/extension/xray.py
coworks/globals.py
coworks/operators.py
coworks/py.typed
coworks/sensors.py
coworks/tech/directory.py
coworks/utils.py
coworks/version.py
coworks/wrappers.py
coworks-0.9.4.dist-info/RECORD
