Metadata-Version: 2.1
Name: coworks
Version: 0.9.4
Summary: CoWorks is a unified compositional microservices framework using Flask/Airflow on AWS serverless technologies.
Keywords: python3,serverless,microservice,flask,airflow,aws-lambda,aws
Author-Email: Guillaume Doumenc <gdoumenc@fpr-coworks.com>
License: MIT License
Classifier: License :: OSI Approved :: MIT License
Classifier: Development Status :: 5 - Production/Stable
Classifier: Intended Audience :: Developers
Classifier: Topic :: System :: Distributed Computing
Classifier: License :: OSI Approved :: MIT License
Classifier: Programming Language :: Python
Classifier: Programming Language :: Python :: 3.11
Project-URL: Documentation, https://coworks.readthedocs.io
Project-URL: Source, https://github.com/gdoumenc/coworks
Requires-Python: >=3.11
Requires-Dist: boto3>=1.19
Requires-Dist: flask>=2.3.0
Requires-Dist: jsonapi-pydantic>=0.2.3
Requires-Dist: markdown>=3.3.6
Requires-Dist: pydantic>=2.5.2
Requires-Dist: pyyaml>=6.0
Requires-Dist: python-dotenv>=0.21.0
Requires-Dist: requests-toolbelt>=0.10
